cssrlib/__init__.py
cssrlib/cssr_bds.py
cssrlib/cssr_has.py
cssrlib/cssr_mdc.py
cssrlib/cssr_pvs.py
cssrlib/cssrlib.py
cssrlib/dgps.py
cssrlib/ephemeris.py
cssrlib/ewss.py
cssrlib/gnss.py
cssrlib/mlambda.py
cssrlib/osnma.py
cssrlib/peph.py
cssrlib/plot.py
cssrlib/pntpos.py
cssrlib/ppp.py
cssrlib/ppprtk.py
cssrlib/pppssr.py
cssrlib/qznma.py
cssrlib/rawnav.py
cssrlib/rinex.py
cssrlib/rtcm.py
cssrlib/rtk.py
cssrlib/sbas.py
cssrlib/tlesim.py
cssrlib/data/30340780.21q
cssrlib/data/3034078M1.21O
cssrlib/data/SEPT078M.21P
cssrlib/data/SEPT078M1.21O
cssrlib/test/test_eph.py
cssrlib/test/test_gnss.py
cssrlib/test/test_peph.py
cssrlib/test/test_rnx.py
cssrlib/test/test_rtk.py
cssrlib-1.2.1.dist-info/licenses/LICENSE
cssrlib-1.2.1.dist-info/METADATA
cssrlib-1.2.1.dist-info/WHEEL
cssrlib-1.2.1.dist-info/top_level.txt
cssrlib-1.2.1.dist-info/RECORD
