Metadata-Version: 2.4
Name: cssrlib
Version: 1.2.1
Summary: Python Toolkit for PPP/PPP-RTK positioning
Home-page: https://github.com/hirokawa/cssrlib
Author: Rui Hirokawa
Author-email: Rui Hirokawa <rui.hirokawa@gmail.com>
Requires-Python: >=3.10
License-File: LICENSE
Requires-Dist: scipy
Requires-Dist: bitstruct
Requires-Dist: galois
Requires-Dist: crccheck
Requires-Dist: notebook
Requires-Dist: numpy
Requires-Dist: matplotlib
Requires-Dist: cartopy
Dynamic: license-file
